TestWidget.py
__init__.py
qroundprogressbar.py
ui_TestWidget.py
qroundprogressbar-1.0.0.dist-info/DESCRIPTION.rst
qroundprogressbar-1.0.0.dist-info/METADATA
qroundprogressbar-1.0.0.dist-info/RECORD
qroundprogressbar-1.0.0.dist-info/WHEEL
qroundprogressbar-1.0.0.dist-info/metadata.json
qroundprogressbar-1.0.0.dist-info/top_level.txt
