Metadata-Version: 2.0
Name: qroundprogressbar
Version: 1.0.0
Summary: PyQt5 port of C++ circular progress bar widget library
Home-page: https://github.com/ozmartian/QRoundProgressBar
Author: Pete Alexandrou
Author-email: pete@ozmartians.com
License: Apache License 2.0
Keywords: qroundprogressbar PyQt PyQt5 QWidget widgets
Platform: UNKNOWN
Classifier: Development Status :: 5 - Production/Stable
Classifier: Environment :: X11 Applications :: Qt
Classifier: Intended Audience :: Developers
Classifier: License :: OSI Approved :: Apache Software License
Classifier: Natural Language :: English
Classifier: Operating System :: OS Independent
Classifier: Programming Language :: Python :: 3 :: Only
